<?xml version="1.0" encoding="UTF-8"?>

<Procedure xmlns="http://hl7.org/fhir">
  <id value="anc-b10-de41-example"/>
  <meta>
    <profile value="http://fhir.org/guides/who/anc-cds/StructureDefinition/anc-b10-de41"/>
  </meta>
  <text>
    <status value="generated"/><div xmlns="http://www.w3.org/1999/xhtml"><p><b>Generated Narrative: Procedure</b><a name="anc-b10-de41-example"> </a></p><div style="display: inline-block; background-color: #d9e0e7; padding: 6px; margin: 4px; border: 1px solid #8da1b4; border-radius: 5px; line-height: 60%"><p style="margin-bottom: 0px">Resource Procedure &quot;anc-b10-de41-example&quot; </p><p style="margin-bottom: 0px">Profile: <a href="StructureDefinition-anc-b10-de41.html">Counselling conducted on use of magnesium and calcium to relieve leg cramps</a></p></div><p><b>identifier</b>: id: anc-b10-de41-example (use: OFFICIAL)</p><p><b>status</b>: completed</p><p><b>code</b>: Counselling conducted on use of magnesium and calcium to relieve leg cramps <span style="background: LightGoldenRodYellow; margin: 4px; border: 1px solid khaki"> (<a href="CodeSystem-anc-custom-codes.html">Extended Codes CodeSystem</a>#ANC.B10.DE41; <a href="http://terminology.hl7.org/3.1.0/CodeSystem-icd10.html">ICD-10</a>#Z71.8 &quot;Other specified counselling&quot;; mms#QA1Y &quot;Contact with health services for other specified counselling&quot;; <a href="https://browser.ihtsdotools.org/">SNOMED CT</a>#410265008 &quot;Medication administration education, guidance, and counseling (procedure)&quot;; ichi#MT1.PP.ZZ &quot;Counselling for neuromusculoskeletal and movement-related functions&quot;)</span></p><p><b>subject</b>: <a href="Patient-anc-patient-example.html">Patient/anc-patient-example</a> &quot; UJM2JA8IGHP1A&quot;</p><p><b>encounter</b>: <a href="Encounter-anc-encounter-example.html">Encounter/anc-encounter-example</a></p><h3>Performers</h3><table class="grid"><tr><td>-</td><td><b>Actor</b></td></tr><tr><td>*</td><td><a href="PractitionerRole-anc-practitionerrole-example.html">PractitionerRole/anc-practitionerrole-example</a></td></tr></table><p><b>location</b>: <a href="Location-anc-location-example.html">Location/anc-location-example</a> &quot;123&quot;</p></div>
  </text>
  <identifier>
    <use value="official"/>
    <system value="http://example.org/fhir/NamingSystem/identifiers"/>
    <value value="anc-b10-de41-example"/>
  </identifier>
  <status value="completed"/>
  <code>
    <coding>
      <system value="http://fhir.org/guides/who/anc-cds/CodeSystem/anc-custom-codes"/>
      <code value="ANC.B10.DE41"/>
      <display value="Counselling conducted on use of magnesium and calcium to relieve leg cramps"/>
    </coding>
    <coding>
      <system value="http://hl7.org/fhir/sid/icd-10"/>
      <code value="Z71.8"/>
      <display value="Other specified counselling"/>
    </coding>
    <coding>
      <system value="http://id.who.int/icd11/mms"/>
      <code value="QA1Y"/>
      <display value="Contact with health services for other specified counselling"/>
    </coding>
    <coding>
      <system value="http://snomed.info/sct"/>
      <code value="410265008"/>
      <display value="Medication administration education, guidance, and counseling (procedure)"/>
    </coding>
    <coding>
      <system value="https://mitel.dimi.uniud.it/ichi/#http://id.who.int/ichi"/>
      <code value="MT1.PP.ZZ"/>
      <display value="Counselling for neuromusculoskeletal and movement-related functions"/>
    </coding>
  </code>
  <subject>
    <reference value="Patient/anc-patient-example"/>
  </subject>
  <encounter>
    <reference value="Encounter/anc-encounter-example"/>
  </encounter>
  <performer>
    <actor>
      <reference value="PractitionerRole/anc-practitionerrole-example"/>
    </actor>
  </performer>
  <location>
    <reference value="Location/anc-location-example"/>
  </location>
</Procedure>